document_merge_service/__init__.py
document_merge_service/api/__init__.py
document_merge_service/api/apps.py
document_merge_service/api/authentication.py
document_merge_service/api/data/2023.test.test.docx-template.docx
document_merge_service/api/data/__init__.py
document_merge_service/api/data/black.png
document_merge_service/api/data/created_with_libreoffice.docx
document_merge_service/api/data/docx-template-filters.docx
document_merge_service/api/data/docx-template-image-placeholder-header-footer.docx
document_merge_service/api/data/docx-template-loopcontrols.docx
document_merge_service/api/data/docx-template-placeholdercheck.docx
document_merge_service/api/data/docx-template-syntax.docx
document_merge_service/api/data/docx-template.docx
document_merge_service/api/data/invalid-template.xlsx
document_merge_service/api/data/loadtest/1.doc
document_merge_service/api/data/loadtest/2.docx
document_merge_service/api/data/loadtest/3.docx
document_merge_service/api/data/loadtest/4.docx
document_merge_service/api/data/odt-template.odt
document_merge_service/api/data/test.txt
document_merge_service/api/data/xlsx-not-valid.xlsx
document_merge_service/api/data/xlsx-structure.xlsx
document_merge_service/api/data/xlsx-syntax.xlsx
document_merge_service/api/data/xlsx-template.xlsx
document_merge_service/api/engines.py
document_merge_service/api/factories.py
document_merge_service/api/file_converter.py
document_merge_service/api/filters.py
document_merge_service/api/jinja.py
document_merge_service/api/management/__init__.py
document_merge_service/api/management/commands/__init__.py
document_merge_service/api/management/commands/clean_dangling_files.py
document_merge_service/api/management/commands/dms_encrypt_templates.py
document_merge_service/api/management/commands/upload_local_templates.py
document_merge_service/api/migrations/0001_initial.py
document_merge_service/api/migrations/0002_template_group.py
document_merge_service/api/migrations/0003_template_meta.py
document_merge_service-9.0.0.dist-info/METADATA
document_merge_service-9.0.0.dist-info/WHEEL
document_merge_service-9.0.0.dist-info/licenses/LICENSE
document_merge_service-9.0.0.dist-info/RECORD
