Metadata-Version: 2.4
Name: document-merge-service
Version: 9.0.0
Summary: Merge Document Template Service
License: GPL-3.0-or-later
License-File: LICENSE
Author: Adfinis AG
Author-email: info@adfinis.com
Requires-Python: >=3.12.0,<3.15
Classifier: Development Status :: 5 - Production/Stable
Classifier: Framework :: Django :: 5
Classifier: Framework :: Django :: 5.2
Classifier: Intended Audience :: Developers
Classifier: License :: OSI Approved :: GNU General Public License v3 or later (GPLv3+)
Classifier: Programming Language :: Python :: 3
Classifier: Programming Language :: Python :: 3.12
Classifier: Programming Language :: Python :: 3.13
Classifier: Programming Language :: Python :: 3.14
Provides-Extra: full
Provides-Extra: slim
Requires-Dist: Babel (>=2.15.0,<3.0.0)
Requires-Dist: Django (>=5.2.7,<5.3.0)
Requires-Dist: Jinja2 (>=3.1.4,<4.0.0)
Requires-Dist: boto3 (>=1.34.143,<2.0.0) ; extra == "full"
Requires-Dist: django-cors-headers (>=4.4.0,<5.0.0)
Requires-Dist: django-environ (>=0.11.2)
Requires-Dist: django-filter (>=24.2)
Requires-Dist: django-generic-api-permissions (>=3.0.0,<4.0.0)
Requires-Dist: django-storages (>=1.14.6,<2.0.0)
Requires-Dist: djangorestframework (>=3.15.2,<4.0.0)
Requires-Dist: docxtpl (>=0.17,<0.21)
Requires-Dist: gunicorn (>=23.0.0,<24.0.0)
Requires-Dist: pillow (>=10.3,<13)
Requires-Dist: poetry (>=2.0.0,<3.0.0)
Requires-Dist: psycopg[binary] (>=3.1.19,<4.0.0) ; extra == "full"
Requires-Dist: pymemcache (>=4.0.0,<5.0.0) ; extra == "full"
Requires-Dist: python-dateutil (>=2.9.0,<3.0.0)
Requires-Dist: python-magic (>=0.4.27,<0.5.0)
Requires-Dist: python-memcached (>=1.59,<2.0)
Requires-Dist: requests (>=2.32.3,<3.0.0)
Requires-Dist: sentry-sdk (>=2.7,<2.50)
Requires-Dist: tqdm (>=4.66.4,<5.0.0)
Requires-Dist: urllib3 (>=2.2.1,<3.0.0)
Requires-Dist: whitenoise (>=6.9.0,<7.0.0)
Requires-Dist: xltpl (>=0.21,<0.22)
Project-URL: Documentation, https://github.com/adfinis/document-merge-service/blob/main/README.md
Project-URL: Homepage, https://github.com/adfinis/document-merge-service
Project-URL: Repository, https://github.com/adfinis/document-merge-service
